pylint_elasticsearch_dsl/__about__.py
pylint_elasticsearch_dsl/__init__.py
pylint_elasticsearch_dsl-0.1.1.dist-info/LICENSE.txt
pylint_elasticsearch_dsl-0.1.1.dist-info/METADATA
pylint_elasticsearch_dsl-0.1.1.dist-info/WHEEL
pylint_elasticsearch_dsl-0.1.1.dist-info/top_level.txt
pylint_elasticsearch_dsl-0.1.1.dist-info/RECORD
