Metadata-Version: 2.1
Name: pylint-elasticsearch-dsl
Version: 0.1.1
Summary: pylint plugin for the elasticsearch-dsl package
Home-page: https://github.com/glostis/pylint-elasticsearch-dsl
Author: Guillaume Lostis
Author-email: g.lostis@kayrros.com
License-File: LICENSE.txt
Requires-Dist: astroid
Provides-Extra: dev
Requires-Dist: bump2version ; extra == 'dev'
Requires-Dist: pre-commit ; extra == 'dev'
Provides-Extra: test
Requires-Dist: pytest ; extra == 'test'
Requires-Dist: pylint ; extra == 'test'
Requires-Dist: elasticsearch-dsl ; extra == 'test'
